workers/__init__.py
workers/admin.py
workers/apps.py
workers/models.py
workers/settings.py
workers/tests.py
workers/util.py
workers/worker.py
workers/management/__init__.py
workers/management/commands/__init__.py
workers/management/commands/runworkers.py
workers/migrations/0001_initial.py
workers/migrations/__init__.py
django_workers-0.2.0.dist-info/LICENSE
django_workers-0.2.0.dist-info/METADATA
django_workers-0.2.0.dist-info/WHEEL
django_workers-0.2.0.dist-info/top_level.txt
django_workers-0.2.0.dist-info/RECORD
