Metadata-Version: 2.1
Name: django-workers
Version: 0.2.0
Summary: Simple background tasks for Django
Home-page: https://github.com/geekforbrains/django-workers
Author: Gavin Vickery
Author-email: gavin@geekforbrains.com
License: UNKNOWN
Platform: UNKNOWN
Classifier: Programming Language :: Python :: 3
Classifier: License :: OSI Approved :: MIT License
Classifier: Operating System :: OS Independent
